k8sfoam/__init__.py
k8sfoam/src/__init__.py
k8sfoam/src/app.py
k8sfoam/src/common/__init__.py
k8sfoam/src/common/dtos.py
k8sfoam/src/frontend/index.html
k8sfoam/src/frontend/index.js
k8sfoam/src/frontend/package-lock.json
k8sfoam/src/frontend/package.json
k8sfoam/src/frontend/style.css
k8sfoam/src/frontend/worker.js
k8sfoam/src/frontend/node_modules/@carrotsearch/foamtree/LICENSE.txt
k8sfoam/src/frontend/node_modules/@carrotsearch/foamtree/README.md
k8sfoam/src/frontend/node_modules/@carrotsearch/foamtree/foamtree.js
k8sfoam/src/frontend/node_modules/@carrotsearch/foamtree/foamtree.min.js
k8sfoam/src/frontend/node_modules/@carrotsearch/foamtree/index.js
k8sfoam/src/frontend/node_modules/@carrotsearch/foamtree/package.json
k8sfoam/src/k8s/__init__.py
k8sfoam/src/k8s/k8s_client.py
k8sfoam/src/utils/__init__.py
k8sfoam/src/utils/extractors.py
k8sfoam/src/utils/mappers.py
k8sfoam/tests/__init__.py
k8sfoam/tests/test_app.py
k8sfoam/tests/common/__init__.py
k8sfoam/tests/common/mocks.py
k8sfoam/tests/k8s/__init__.py
k8sfoam/tests/k8s/test_k8s_client.py
k8sfoam/tests/utils/__init__.py
k8sfoam/tests/utils/test_extractors.py
k8sfoam/tests/utils/test_mappers.py
k8sfoams-1.2.1.dist-info/METADATA
k8sfoams-1.2.1.dist-info/WHEEL
k8sfoams-1.2.1.dist-info/entry_points.txt
k8sfoams-1.2.1.dist-info/licenses/LICENSE
k8sfoams-1.2.1.dist-info/RECORD
