Metadata-Version: 2.4
Name: k8sfoams
Version: 1.2.1
Summary: K8s pod foamtree visualizer
Project-URL: Homepage, https://github.com/mmpyro/k8s-pod-foamtree
Author-email: Michal Marszalek <mmpyro@gmail.com>
License: Apache 2.0
License-File: LICENSE
Keywords: foamtree,k8s,visualization
Classifier: Development Status :: 3 - Alpha
Classifier: License :: OSI Approved :: Apache Software License
Classifier: Programming Language :: Python :: 3.9
Classifier: Topic :: Scientific/Engineering :: Visualization
Requires-Python: >=3.9
Requires-Dist: bitmath>=1.3.3.1
Requires-Dist: flask>=3.1.0
Requires-Dist: kubernetes>=32.0.0
Requires-Dist: pydash>=8.0.4
Requires-Dist: requests>=2.32.3
Provides-Extra: dev
Requires-Dist: bandit>=1.8.0; extra == 'dev'
Requires-Dist: flake8>=7.1.1; extra == 'dev'
Requires-Dist: mock>=5.1.0; extra == 'dev'
Requires-Dist: mypy>=1.14.1; extra == 'dev'
Requires-Dist: pytest>=8.3.4; extra == 'dev'
